{
  "PACS_Report": {
    "Extraction_Timestamp": "14/02/2023 17:32:20",
    "Patient": {
      "ID": "1830199201471769552",
      "Birthdate": "04/11/1960"
    },
    "Report": {
      "AccessionNumber": "142021261712",
      "Exam_Type": "TC, adicional de Angio TC",
      "Observation": "{\\rtf1\\ansi\\ansicpg1252\\deff0\\nouicompat\\deflang2057{\\fonttbl{\\f0\\fnil\\fcharset0 Arial;}{\\f1\\fnil\\fcharset0 Arial;}}{\\*\\JS CHULN 2020}\\viewkind4\\uc1\\pard\\qj\\f1\\fs24\\lang2070 Homem de 60 anos, com AP de DPOC tab\\'e1gica (predom\\'ednio de enfisema), sequelas de TP, crioglobulin\\'e9mia mista tipo II.\\par Internado na UCIR por Pneumonia SARS-CoV2 com componente organizativo e sobre-infe\\'e7\\'e3o bacteriana. \\'c0 data de internamento, houve suspeita de ITU; associadamente apresentava LRA AKIN II, entretanto resolvida.\\par Na AngioTC-t\\'f3rax inicial foi exclu\\'eddo TEP central, mas entretanto o doente iniciou subida de DD (m\\'e1x. 25). Concomitantemente, o doente agravou do ponto de vista respirat\\'f3rio com necessidade de VMI ontem (D19 doen\\'e7a COVID-19). \\par No estudo anal\\'edtico de hoje, apresenta subida de PI\\'27s e ligeira descida de DD (16); do ponto de vista cl\\'ednico, com urina concentrada e com sedimento e sem melhoria do componente respirat\\'f3rio.\\par Pe\\'e7o AngioTC-t\\'f3rax e TC-AP, para esclarecimento do quadro, nomeadamente exclus\\'e3o de TEP e identifica\\'e7\\'e3o de eventual foco infecioso urin\\'e1rio.\\par}",
      "Report": "{\\rtf1\\ansi\\ansicpg1252\\deff0\\deflang1053{\\fonttbl{\\f0\\fnil\\fcharset0 Arial;}} \\viewkind4\\uc1\\pard\\lang2070\\f0\\fs24Angio-TC tor\\'e1cica + TC abdominal e p\\'e9lvica urgente\\par \\par Aquisi\\'e7\\'e3o volum\\'e9trica dos \\'e1pices pulmonares at\\'e9 \\'e0 s\\'ednfise p\\'fabica ap\\'f3s injec\\'e7\\'e3o endovenosa de contraste iodado, com protocolo dirigido ao estudo permeabilidade arterial pulmonar. Reconstru\\'e7\\'f5es multiplanares de 1 e 3 mm de espessura em algoritmo de pulm\\'e3o e partes moles respectivamente.\\par Tivemos acesso a exames pr\\'e9vios, o mais recente de 30/09/2021.\\par \\par Observam-se defeitos de reple\\'e7\\'e3o de ramos arteriais pulmonares e subsegmentares em ambos os lobos inferiores, aspectos compat\\'edveis com tromboembolismo pulmonar bilateral. Tronco arterial pulmonar com calibre normal.\\par L\\'e2mina de l\\'edquido peric\\'e1rdico.\\par Cateter na veia jugular direita com extremidade no tronco venoso braquio-cef\\'e1lico homolateral.\\par Fina l\\'e2mina de l\\'edquido pleural esquerdo.\\par Persist\\'eancia das \\'e1reas de densifica\\'e7\\'e3o em vidro despolido e espessamento septal do par\\'eanquima pulmonar, compat\\'edveis com pneumonia COVID-19 (cerca 30 a 50% par\\'eanquima). Refere-se, na presente avalia\\'e7\\'e3o, aumento da express\\'e3o consolidativa em topografia p\\'f3stero-basal, que embora com poss\\'edvel componente atelect\\'e1sico se admite em mais prov\\'e1vel rela\\'e7\\'e3o com \\'e1reas de pneumonia organizativa. Evidente hetergeneidade do realce do par\\'eanquima consolidado, com zona de hiporealce mais not\\'f3ria em topografia p\\'f3stero-interna esquerda, indiciando \\'e1reas de enfarte parenquimatoso. \\par Enfisema moderado a grave de predom\\'ednio centrilobular.\\par \\'c1rvore traqueobr\\'f4nquica proximal perme\\'e1vel e de calibre mantido.\\par Entuba\\'e7\\'e3o traqueal com extremidade a cerca de 4,5 cm da carina.\\par Algumas bronquiectasias cil\\'edndricas em localiza\\'e7\\'e3o apical direita, a que se associa \\'e1rea de consolida\\'e7\\'e3o retr\\'e1ctil do par\\'eanquima subpleural, traduzindo fen\\'f3menos de mais prov\\'e1vel natureza cicatricial.\\par \\par Pequenos g\\'e2nglios mediast\\'ednicos globalmente infracentim\\'e9tricos.\\par F\\'edgado com dimens\\'f5es preservadas, contornos bosselados e densidade globalmente homog\\'e9nea. Ligeira proemin\\'eancia das vias biliares intra hep\\'e1ticas. Sem ectasia da VBP ou tradu\\'e7\\'e3o de obst\\'e1culo por este m\\'e9todo. Imagem.\\par Vesicula biliar em reple\\'e7\\'e3o, sem espessamento parietal ou sinais de lit\\'edase por este m\\'e9todo.\\par Ba\\'e7o normodimensionado e homog\\'e9neo. N\\'e3o se observam altera\\'e7\\'f5es morfoestruturais das gl\\'e2ndulas supra-renais e do p\\'e2ncreas, excepto por discreta proemin\\'eancia do calibre do canal pancre\\'e1tico cef\\'e1lico.\\par Rins com dimens\\'f5es preservadas, contornos bosselados e boa espessura parenquimatosa. Pequenas forma\\'e7\\'f5es qu\\'edsticas corticais. Sem dilata\\'e7\\'e3o das \\'e1rvores excretoras renais.\\par Bexiga em fraca reple\\'e7\\'e3o sem altera\\'e7\\'f5es por este m\\'e9todo. Aumento dimensional e heterogeneidade prost\\'e1tica.\\par Pequena quantidade de l\\'edquido livre intraperitoneal p\\'e9lvico e nos quadrantes direitos. Regular tradu\\'e7\\'e3o do eixo aortocava.\\par N\\'e3o se observam adenomegalias lombo-a\\'f3rticas ou p\\'e9lvicas.\\par Sem distens\\'e3o c\\'f3lica ou de ansas de delgado.\\par Densifica\\'e7\\'e3o heterog\\'e9nea do plano adiposo na parede abdominal infra-umbilical mediana e paramediana esquerda a valorizar clinicamente (hematoma?)\\par \\par Dr\\'aa Dulce Antunes \\par \\par } ",
      "Validation_Timestamp": "06/10/2021 18:38:54"
    }
  }
}